anydoor/consoles/__init__.py
anydoor/consoles/application.py
anydoor/consoles/chat.py
anydoor/consoles/secrets.py
anydoor/dbs/__init__.py
anydoor/dbs/base.py
anydoor/dbs/clickhouse.py
anydoor/dbs/postgres.py
anydoor/dbs/sqlite.py
anydoor/llms/__init__.py
anydoor/llms/conversation/__init__.py
anydoor/llms/conversation/chat.py
anydoor/llms/conversation/template/__init__.py
anydoor/llms/conversation/template/default.py
anydoor/llms/functions/__init__.py
anydoor/llms/functions/cost.py
anydoor/llms/functions/token.py
anydoor/llms/prompts/__init__.py
anydoor/llms/prompts/base.py
anydoor/llms/prompts/joke_creater.py
anydoor/utils/__init__.py
anydoor/utils/check.py
anydoor/utils/container.py
anydoor/utils/log.py
anydoor/utils/message/__init__.py
anydoor/utils/message/base.py
anydoor/utils/message/feishu.py
anydoor/utils/message/qywx.py
anydoor/utils/message/telegram.py
anydoor/utils/proxy.py
anydoor/utils/secret.py
anydoor/utils/singleton.py
anydoor/utils/time.py
anydoor-0.1.2.dist-info/METADATA
anydoor-0.1.2.dist-info/WHEEL
anydoor-0.1.2.dist-info/entry_points.txt
anydoor-0.1.2.dist-info/RECORD
