Metadata-Version: 2.1
Name: anydoor
Version: 0.1.2
Summary: Anydoor to any cozy functions and classes. Suitable for data and llm
Home-page: https://github.com/veinkr/Anydoor
Keywords: anydoor
Author: veinkr
Author-email: yhf2lj@gmail.com
Requires-Python: >=3.10,<4.0
Classifier: Programming Language :: Python :: 3
Classifier: Programming Language :: Python :: 3.10
Classifier: Programming Language :: Python :: 3.11
Classifier: Programming Language :: Python :: 3.12
Requires-Dist: SQLAlchemy (>2.0)
Requires-Dist: cleo (>=2.1.0,<3.0.0)
Requires-Dist: clickhouse-sqlalchemy (>=0.3.1,<0.4.0)
Requires-Dist: colorama (>=0.4.6,<0.5.0)
Requires-Dist: cryptography (>=42.0.5,<43.0.0)
Requires-Dist: fastapi (>=0.110.1,<0.111.0)
Requires-Dist: langchain (>=0.1.16,<0.2.0)
Requires-Dist: langchain-openai (>=0.1.3,<0.2.0)
Requires-Dist: numpy (>=1.26.4,<2.0.0)
Requires-Dist: pandas (>=2.2.2,<3.0.0)
Requires-Dist: psycopg2-binary (>=2.9.9,<3.0.0)
Requires-Dist: rich (>=13.7.1,<14.0.0)
Requires-Dist: tenacity (>=8.2.3,<9.0.0)
Project-URL: Changelog, https://github.com/veinkr/Anydoor/commits/main/
Project-URL: Documentation, https://github.com/veinkr/Anydoor/blob/main/README.md
Project-URL: Repository, https://github.com/veinkr/Anydoor
